README.rst
setup.py
hesiod53/__init__.py
hesiod53/ssh.py
hesiod53/sync.py
hesiod53.egg-info/PKG-INFO
hesiod53.egg-info/SOURCES.txt
hesiod53.egg-info/dependency_links.txt
hesiod53.egg-info/entry_points.txt
hesiod53.egg-info/requires.txt
hesiod53.egg-info/top_level.txt