Metadata-Version: 1.1
Name: hesiod53
Version: 0.1.0
Summary: Utilities for using hesiod with route53
Home-page: https://github.com/fullcontact/hesiod53
Author: FullContact
Author-email: ops+hesiod53@fullcontact.com
License: MIT
Keywords: ssh
Platform: UNKNOWN
Classifier: Development Status :: 3 - Alpha
Classifier: Intended Audience :: Developers
Classifier: Intended Audience :: System Administrators
Classifier: Topic :: System :: Systems Administration :: Authentication/Directory
Classifier: Operating System :: POSIX :: Linux
Classifier: License :: OSI Approved :: MIT License
Classifier: Programming Language :: Python :: 2
Classifier: Programming Language :: Python :: 2.6
Classifier: Programming Language :: Python :: 2.7
